mariana_trench/__init__.py
mariana_trench/shim/__init__.py
mariana_trench/shim/configuration.py
mariana_trench/shim/exit_codes.py
mariana_trench/shim/package.py
mariana_trench/shim/shim.py
mariana_trench-1.0.7.data/data/bin/mariana-trench-binary
mariana_trench-1.0.7.data/data/share/mariana-trench/configuration/default_generator_config.json
mariana_trench-1.0.7.data/data/share/mariana-trench/configuration/default_system_jar_paths.json
mariana_trench-1.0.7.data/data/share/mariana-trench/configuration/lifecycles.json
mariana_trench-1.0.7.data/data/share/mariana-trench/configuration/rules.json
mariana_trench-1.0.7.data/data/share/mariana-trench/configuration/shims.json
mariana_trench-1.0.7.data/data/share/mariana-trench/configuration/filters/3-intent-redirect-filter.json
mariana_trench-1.0.7.data/data/share/mariana-trench/configuration/filters/exported-component-filter.json
mariana_trench-1.0.7.data/data/share/mariana-trench/configuration/model-generators/propagations/AndroidGettersAndSettersGenerator.models
mariana_trench-1.0.7.data/data/share/mariana-trench/configuration/model-generators/propagations/DataCastFeatureGenerator.models
mariana_trench-1.0.7.data/data/share/mariana-trench/configuration/model-generators/propagations/ExplicitIntentFeatureGenerator.models
mariana_trench-1.0.7.data/data/share/mariana-trench/configuration/model-generators/propagations/IntentDataFeatureGenerator.models
mariana_trench-1.0.7.data/data/share/mariana-trench/configuration/model-generators/propagations/UrlEncodeFeatureGenerator.models
mariana_trench-1.0.7.data/data/share/mariana-trench/configuration/model-generators/sanitizers/CommonSanitizers.models
mariana_trench-1.0.7.data/data/share/mariana-trench/configuration/model-generators/sinks/ActivityResultGenerator.models
mariana_trench-1.0.7.data/data/share/mariana-trench/configuration/model-generators/sinks/AndroidIntentLaunchSinkGenerator.models
mariana_trench-1.0.7.dist-info/METADATA
mariana_trench-1.0.7.dist-info/WHEEL
mariana_trench-1.0.7.dist-info/entry_points.txt
mariana_trench-1.0.7.dist-info/top_level.txt
mariana_trench-1.0.7.dist-info/RECORD
