Metadata-Version: 2.4
Name: mariana-trench
Version: 1.0.7
Summary: A security focused static analysis platform targeting Android.
Home-page: https://mariana-tren.ch/
Download-URL: https://github.com/facebook/mariana-trench
Author: Facebook
Author-email: pyre@fb.com
Maintainer: Facebook
Maintainer-email: pyre@fb.com
License: MIT
Keywords: security,taint,flow,static,analysis,android,java
Classifier: Development Status :: 5 - Production/Stable
Classifier: Environment :: Console
Classifier: Intended Audience :: Developers
Classifier: License :: OSI Approved :: MIT License
Classifier: Operating System :: MacOS
Classifier: Operating System :: POSIX :: Linux
Classifier: Programming Language :: Python
Classifier: Programming Language :: Python :: 3
Classifier: Programming Language :: Python :: 3.6
Classifier: Programming Language :: C++
Classifier: Topic :: Security
Classifier: Topic :: Software Development
Classifier: Typing :: Typed
Requires-Python: >=3.6
Requires-Dist: pyre_extensions
Requires-Dist: fb-sapp
Dynamic: download-url
